triangle_drawer/__init__.py
triangle_drawer/drawer.py
triangle_drawer_yx-0.1.0.dist-info/METADATA
triangle_drawer_yx-0.1.0.dist-info/WHEEL
triangle_drawer_yx-0.1.0.dist-info/top_level.txt
triangle_drawer_yx-0.1.0.dist-info/RECORD
