Metadata-Version: 2.1
Name: triangle_drawer_yx
Version: 0.1.0
Summary: A package to draw colored triangles in console.
Home-page: https://github.com/Skillsyx
Author: Yuan Xin
Author-email: yxskills46@gmail.com
Classifier: Programming Language :: Python :: 3
Classifier: License :: OSI Approved :: MIT License
Classifier: Operating System :: OS Independent
Requires-Python: >=3.6
Requires-Dist: termcolor
